CHANGES.md
CLASSIFIERS.txt
ENTRY_POINTS.ini
LICENSE.md
MANIFEST.in
README.md
development.ini
setup.cfg
setup.py
Vaktuk.egg-info/PKG-INFO
Vaktuk.egg-info/SOURCES.txt
Vaktuk.egg-info/dependency_links.txt
Vaktuk.egg-info/entry_points.txt
Vaktuk.egg-info/not-zip-safe
Vaktuk.egg-info/requires.txt
Vaktuk.egg-info/top_level.txt
vaktuk/__init__.py
vaktuk/extensibility.py
vaktuk/resources.py
vaktuk/views.py
vaktuk/wsgi.py