Metadata-Version: 1.0
Name: Vaktuk
Version: 0.0.1
Summary: Content management in Pyramid
Home-page: http://vatuk.limpidtech.com/
Author: Brandon R. Stoner
Author-email: monokrome@limpidtech.com
License: UNKNOWN
Keywords: web pylons pyramid
Platform: UNKNOWN
